djhtcpcp/__init__.py
djhtcpcp/middleware.py
django_htcpcp-0.2.7.dist-info/METADATA
django_htcpcp-0.2.7.dist-info/WHEEL
django_htcpcp-0.2.7.dist-info/top_level.txt
django_htcpcp-0.2.7.dist-info/RECORD
